include/zdict.h
include/zstd_errors.h
include/zstd.h
data_logger/_core.cpython-313-darwin.so
data_logger/_core.pyi
data_logger/periodic.py
data_logger/_core.cpp
data_logger/__init__.py
data_logger/py.typed
data_logger/main.py
data_logger/cpp/ringbuffer.hpp
data_logger/cpp/sparse.hpp
data_logger/cpp/varint.hpp
data_logger/cpp/stream_frame.hpp
data_logger/cpp/segment_writer.hpp
lib/libzstd.1.5.6.dylib
lib/libzstd.a
lib/libzstd.1.dylib
lib/libzstd.dylib
lib/pkgconfig/libzstd.pc
lib/cmake/zstd/zstdConfigVersion.cmake
lib/cmake/zstd/zstdTargets.cmake
lib/cmake/zstd/zstdConfig.cmake
lib/cmake/zstd/zstdTargets-release.cmake
disco_data_logger-0.1.1.dist-info/RECORD
disco_data_logger-0.1.1.dist-info/WHEEL
disco_data_logger-0.1.1.dist-info/METADATA
disco_data_logger-0.1.1.dist-info/licenses/LICENSE
